odoo10_addon_website_sale_charge_payment_fee_delivery-10.0.1.0.0.99.dev5-py3.8-nspkg.pth
odoo/addons/website_sale_charge_payment_fee_delivery/README.rst
odoo/addons/website_sale_charge_payment_fee_delivery/__init__.py
odoo/addons/website_sale_charge_payment_fee_delivery/__manifest__.py
odoo/addons/website_sale_charge_payment_fee_delivery/controllers/__init__.py
odoo/addons/website_sale_charge_payment_fee_delivery/controllers/website_sale.py
odoo/addons/website_sale_charge_payment_fee_delivery/i18n/it.po
odoo/addons/website_sale_charge_payment_fee_delivery/i18n/website_sale_charge_payment_fee_delivery.pot
odoo/addons/website_sale_charge_payment_fee_delivery/models/__init__.py
odoo/addons/website_sale_charge_payment_fee_delivery/models/delivery.py
odoo/addons/website_sale_charge_payment_fee_delivery/readme/CONTRIBUTORS.rst
odoo/addons/website_sale_charge_payment_fee_delivery/readme/DESCRIPTION.rst
odoo/addons/website_sale_charge_payment_fee_delivery/static/description/icon.png
odoo/addons/website_sale_charge_payment_fee_delivery/static/description/index.html
odoo10_addon_website_sale_charge_payment_fee_delivery-10.0.1.0.0.99.dev5.dist-info/METADATA
odoo10_addon_website_sale_charge_payment_fee_delivery-10.0.1.0.0.99.dev5.dist-info/WHEEL
odoo10_addon_website_sale_charge_payment_fee_delivery-10.0.1.0.0.99.dev5.dist-info/namespace_packages.txt
odoo10_addon_website_sale_charge_payment_fee_delivery-10.0.1.0.0.99.dev5.dist-info/top_level.txt
odoo10_addon_website_sale_charge_payment_fee_delivery-10.0.1.0.0.99.dev5.dist-info/RECORD
